pyscissor/__init__.py
pyscissor/helper.py
pyscissor/pinpoint.py
pyscissor/scissor.py
pyscissor-1.1.7.data/scripts/nc2ts_by_shp.cmd
pyscissor-1.1.7.data/scripts/nc2ts_by_shp.py
pyscissor-1.1.7.data/scripts/nc2ts_by_xy.cmd
pyscissor-1.1.7.data/scripts/nc2ts_by_xy.py
pyscissor-1.1.7.dist-info/LICENSE
pyscissor-1.1.7.dist-info/METADATA
pyscissor-1.1.7.dist-info/WHEEL
pyscissor-1.1.7.dist-info/top_level.txt
pyscissor-1.1.7.dist-info/RECORD
