Metadata-Version: 2.1
Name: pyscissor
Version: 1.1.7
Summary: A python module for obtaining reduced(min,max,avg) value from netCDF file under a polygon region
Home-page: https://github.com/nzahasan/pyscissor
Author: nzahasan
Author-email: nzahasan@gmail.com
License: MIT
Keywords: netcdf,crop,shapefile
Requires-Python: >=3.6
License-File: LICENSE
Requires-Dist: numpy
Requires-Dist: netCDF4
Requires-Dist: shapely
Requires-Dist: fiona
Requires-Dist: pandas
Requires-Dist: yaspin
